network_optimisation/__init__.py
network_optimisation/hitchcockproblem.py
steelo/__init__.py
steelo/bootstrap.py
steelo/config.py
steelo/devdata.py
steelo/py.typed
steelo/simulation.py
steelo/adapters/__init__.py
steelo/adapters/geospatial.py
steelo/adapters/dataprocessing/__init__.py
steelo/adapters/dataprocessing/excel_reader.py
steelo/adapters/dataprocessing/infrastructure_data.py
steelo/adapters/dataprocessing/preprocessing/__init__.py
steelo/adapters/dataprocessing/preprocessing/cost_of_x_data_processing.py
steelo/adapters/dataprocessing/preprocessing/dynamic_business_case_prep.py
steelo/adapters/dataprocessing/preprocessing/iso3_finder.py
steelo/adapters/dataprocessing/preprocessing/laea_crs_finder.py
steelo/adapters/dataprocessing/preprocessing/raw_plant_data_processing.py
steelo/adapters/dataprocessing/preprocessing/technology_switch.py
steelo/adapters/repositories/__init__.py
steelo/adapters/repositories/in_memory_repository.py
steelo/adapters/repositories/interface.py
steelo/adapters/repositories/json_repository.py
steelo/domain/BOM.py
steelo/domain/Capex.py
steelo/domain/__init__.py
steelo/domain/asset_economic_decision.py
steelo/domain/calculate_costs.py
steelo/domain/commands.py
steelo/domain/constants.py
steelo/domain/datacollector.py
steelo/domain/dbom.py
steelo/domain/environment.py
steelo/domain/events.py
steelo/domain/expansion_eval.py
steelo/domain/models.py
steelo/domain/mappings/__init__.py
steelo/domain/mappings/country.py
steelo/domain/trade_modelling/hitchcock_modelling.py
steelo/economic_models/__init__.py
steelo/economic_models/cost_of_renewables.py
steelo/economic_models/dummy.py
steelo/economic_models/interface.py
steelo/economic_models/plant_agent.py
steelo/entrypoints/__init__.py
steelo/entrypoints/cli.py
steelo/fixtures/Data_collection_ultimate_steel.xlsx
steelo/fixtures/cost_of_x.json
steelo/fixtures/countries.csv
steelo/fixtures/gravity_distances.csv
steelo/fixtures/plants.json
steelo/fixtures/technology_lcop.csv
steel_model-0.1.1.dist-info/METADATA
steel_model-0.1.1.dist-info/WHEEL
steel_model-0.1.1.dist-info/entry_points.txt
steel_model-0.1.1.dist-info/RECORD
